
{"bookId":"","ISBN":"33333333333","title":"Advanced cSharp","author":"Esunew","publisher":"demmelash pub","edition":"3rd Edition","price":25.25,"imagePath":"resources/images/cSharp.png","quantity":0}
{"bookId":"","ISBN":"888888","title":"software","author":"aaaaa","publisher":"ppppppp","edition":"eeeeeeee","price":555555.0,"imagePath":"resources/images/cSharp.png","quantity":0}
{"bookId":"","ISBN":"444444444","title":"Html5","author":"lema","publisher":"Esubalew Pub","edition":"FirstEdition1","price":50.5,"imagePath":"resources/images/android.png","quantity":0}